icreports/__init__.py
icreports/content.py
icreports/hyperlink.py
icreports/link_validator.py
icreports/main_cli.py
icreports/py.typed
icreports/spellcheck.py
icreports/tags.py
icreports/document/__init__.py
icreports/document/chapter.py
icreports/document/config.py
icreports/document/part.py
icreports/document/section.py
icreports/document/toc.py
icreports/document/jupyter_book/__init__.py
icreports/document/jupyter_book/chapter.py
icreports/document/jupyter_book/part.py
icreports/document/jupyter_book/section.py
icreports/document/jupyter_book/toc.py
icreports/rendering/__init__.py
icreports/rendering/book.py
icreports/rendering/context.py
icreports/rendering/document.py
icreports/rendering/media.py
icreports/rendering/rendering.py
icreports-0.0.16.dist-info/licenses/LICENSE
icreports-0.0.16.dist-info/METADATA
icreports-0.0.16.dist-info/WHEEL
icreports-0.0.16.dist-info/entry_points.txt
icreports-0.0.16.dist-info/top_level.txt
icreports-0.0.16.dist-info/RECORD
