Metadata-Version: 2.4
Name: icreports
Version: 0.0.16
Summary: Utilities for generating technical reports.
Author-email: "James Grogan, Irish Centre for High End Computing" <james.grogan@ichec.ie>
Project-URL: Repository, https://git.ichec.ie/performance/toolshed/icreports
Project-URL: Homepage, https://git.ichec.ie/performance/toolshed/icreports
Keywords: Publishing,Technical Reports
Classifier: Development Status :: 3 - Alpha
Classifier: Programming Language :: Python :: 3
Classifier: License :: OSI Approved :: GNU General Public License v3 or later (GPLv3+)
Classifier: Operating System :: OS Independent
Classifier: Topic :: System :: Distributed Computing
Requires-Python: >=3.10
License-File: LICENSE
Requires-Dist: icplot[cairo]==0.1.5
Requires-Dist: ictasks==0.1.5
Requires-Dist: markdown-it-py
Requires-Dist: mdit_py_plugins
Requires-Dist: mdformat
Requires-Dist: beautifulsoup4
Requires-Dist: pyspelling
Requires-Dist: jupyter-book
Provides-Extra: test
Requires-Dist: pytest; extra == "test"
Requires-Dist: pytest-cov; extra == "test"
Requires-Dist: pytest-sugar; extra == "test"
Requires-Dist: black; extra == "test"
Requires-Dist: mypy; extra == "test"
Requires-Dist: flake8; extra == "test"
Requires-Dist: pylint; extra == "test"
Provides-Extra: types
Requires-Dist: types-PyYAML; extra == "types"
Dynamic: license-file
